{
  "C:\\Users\\Jalal\\Desktop\\S3\\NLP\\NLP-Java-workspace\\MyNLPServer\\src\\data\\data_test\\AR_01.txt": {
    "الجمال": 1,
    "الإنسانية": 1,
    "للمشكلات": 1,
    "تضمن": 1,
    "العلمية": 1,
    "الإبداع": 1,
    "حلول": 1,
    "الاصطناعي": 6,
    "الخير": 1,
    "تقنيات": 1,
    "وسرقة": 1,
    "كميات": 1,
    "التغير": 1,
    "ا": 8,
    "مختلفة": 1,
    "الإنسان": 3,
    "ت": 1,
    "يمكن": 3,
    "أطر": 1,
    "يتحدث": 1,
    "ر": 1,
    "أنظمة": 1,
    "الخدمات": 1,
    "أدبية": 1,
    "الذكية": 2,
    "تبتكر": 1,
    "البيانات": 3,
    "أساليب": 1,
    "نكتب": 1,
    "يخشى": 1,
    "فرصة": 1,
    "أهمية": 1,
    "الأخيرة": 1,
    "التسوق": 1,
    "عظيمة": 1,
    "النجاح": 1,
    "المؤسسات": 1,
    "مواقع": 1,
    "التساؤلات": 1,
    "نقاش": 1,
    "كبيرة": 1,
    "التعلم": 1,
    "وتضمن": 1,
    "كفاءة": 1,
    "الحسابات": 1,
    "وصور": 1,
    "يؤدي": 1,
    "استخدام": 2,
    "وقت": 1,
    "وفي": 3,
    "التكنولوجيا": 1,
    "يعيش": 1,
    "تتداخل": 1,
    "اليومية": 1,
    "وحماية": 1,
    "الأمر": 1,
    "الفجوة": 1,
    "اختراق": 1,
    "سن": 1,
    "واضحة": 1,
    "الوظائف": 1,
    "الخبراء": 1,
    "التوصية": 1,
    "الذكاء": 6,
    "سيد": 1,
    "تزايد": 1,
    "زاد": 1,
    "أم": 1,
    "الخوارزميات": 1,
    "تراجع": 1,
    "التحديات": 1,
    "البعض": 1,
    "منازلنا": 1,
    "فمع": 1,
    "بينها": 1,
    "قدرات": 1,
    "يومي": 1,
    "أيض": 1,
    "البشرية": 2,
    "نحو": 1,
    "ذكية": 1,
    "الهواتف": 1,
    "المجال": 1,
    "الأبحاث": 1,
    "ملايين": 1,
    "للإنسان": 1,
    "يغير": 1,
    "إيجاد": 1,
    "معنى": 1,
    "وتحليل": 1,
    "القيادة": 1,
    "أعمال": 1,
    "أداة": 1,
    "الخصوصية": 1,
    "الرقمية": 1,
    "والاجتماعية": 1,
    "المساعدات": 1,
    "فمن": 1,
    "للآلة": 1,
    "فقدان": 1,
    "الرغم": 1,
    "الدراسات": 1,
    "الموارد": 1,
    "فهناك": 1,
    "وإلى": 2,
    "وأن": 1,
    "قوانين": 1,
    "جاهدة": 1,
    "تسعى": 1,
    "الأخطاء": 1,
    "هل": 1,
    "الصحية": 1,
    "المفرط": 1,
    "عالم": 1,
    "الهوية": 1,
    "مدى": 1,
    "لمحاولات": 1,
    "برامج": 1,
    "الدول": 1,
    "وبين": 1,
    "ومن": 1,
    "تسريع": 1,
    "فنية": 1,
    "صارمة": 1,
    "والتعليمية": 1,
    "يطرح": 1,
    "فهو": 1,
    "يثير": 1,
    "بها": 1,
    "يمثل": 1,
    "أخرى": 1,
    "تسهم": 1,
    "واتخاذ": 1,
    "السيارات": 1,
    "الجانب": 1,
    "الضروري": 1,
    "الاستراتيجية": 1,
    "الحياة": 1,
    "هائلة": 1,
    "قوية": 1,
    "يبقى": 1,
    "السنوات": 1,
    "ظهر": 1,
    "تتعرض": 1,
    "تأليف": 1,
    "بنسبة": 1,
    "فيه": 1,
    "البشر": 1,
    "حكر": 1,
    "نصوص": 1,
    "يعتمد": 1,
    "ووضع": 1,
    "اتساع": 1,
    "المتقدمة": 1,
    "حماية": 1,
    "مسألة": 2,
    "الكتاب": 1,
    "يجعل": 1,
    "ونقص": 1,
    "القيم": 1,
    "المعالجة": 1,
    "جزء": 1,
    "وأخرى": 1,
    "تحسين": 1,
    "قادرة": 1,
    "والمستشفيات": 1,
    "الشفافية": 1,
    "والموسيقى": 1,
    "حياتنا": 1,
    "بطرق": 1,
    "واقعية": 1,
    "ذاتية": 1,
    "المشهورين": 1,
    "الفنانين": 1,
    "المعقدة": 1,
    "تصبح": 1,
    "وتقليد": 1,
    "المصانع": 1,
    "ترفع": 1,
    "تنتج": 1,
    "بيئة": 1,
    "وتعب": 1,
    "القرارات": 1,
    "توجيه": 1,
    "خادم": 1,
    "فلسفي": 1,
    "تنظم": 1,
    "الشعر": 1,
    "أخلاقية": 1,
    "الآلات": 1,
    "والدول": 1,
    "تحليل": 1,
    "والأمراض": 1,
    "للاستفادة": 1,
    "التطور": 1,
    "الصوتية": 1,
    "الآلي": 1,
    "الاعتماد": 2,
    "الثقافي": 1,
    "يتفق": 1,
    "يتجزأ": 1,
    "التمييز": 1,
    "والروايات": 1,
    "تفاصيل": 1,
    "مضى": 1,
    "الإنترنت": 1,
    "الباحثين": 1,
    "المستعصية": 1,
    "جمع": 1,
    "العمل": 2,
    "النامية": 1,
    "لتطوير": 1,
    "دولية": 1,
    "المعلومات": 1,
    "العديد": 2,
    "الطريقة": 1,
    "تقليل": 1,
    "بدأ": 1,
    "لوحات": 1,
    "الأخلاقية": 1,
    "قدرة": 1,
    "المذهل": 1,
    "جهة": 2,
    "أغلب": 1,
    "وتساعد": 1,
    "المناخي": 1,
    "التقنيات": 1
  }
}